rye_hello/__init__.py
rye_hello/main.py
rye_hello-0.1.2.dist-info/METADATA
rye_hello-0.1.2.dist-info/WHEEL
rye_hello-0.1.2.dist-info/RECORD
