Metadata-Version: 2.3
Name: rye-hello
Version: 0.1.2
Summary: test import lib
Requires-Python: >=3.8
